gundi_client_v2/__init__.py
gundi_client_v2/auth.py
gundi_client_v2/client.py
gundi_client_v2/errors.py
gundi_client_v2/settings.py
gundi_client_v2-2.4.1.dist-info/METADATA
gundi_client_v2-2.4.1.dist-info/WHEEL
gundi_client_v2-2.4.1.dist-info/RECORD
